goa/__init__.py
goa/__main__.py
goa/algorithms.py
goa/cli.py
goa/problems.py
goa/utils.py
goa-0.1.1.dist-info/LICENSE
goa-0.1.1.dist-info/WHEEL
goa-0.1.1.dist-info/METADATA
goa-0.1.1.dist-info/RECORD
